server/__init__.py
server/kb_mcp_server.py
volcengine_knowledgebase_mcp-0.1.0.dist-info/licenses/LICENSE
volcengine_knowledgebase_mcp-0.1.0.dist-info/METADATA
volcengine_knowledgebase_mcp-0.1.0.dist-info/WHEEL
volcengine_knowledgebase_mcp-0.1.0.dist-info/entry_points.txt
volcengine_knowledgebase_mcp-0.1.0.dist-info/top_level.txt
volcengine_knowledgebase_mcp-0.1.0.dist-info/RECORD
