Metadata-Version: 2.4
Name: volcengine-knowledgebase-mcp
Version: 0.1.0
Summary: Add your description here
Requires-Python: >=3.13
License-File: LICENSE
Requires-Dist: mcp[cli]>=1.5.0
Requires-Dist: requests>=2.31.0
Requires-Dist: volcengine>=1.0.0
Dynamic: license-file
